ceda_flight_pipeline/__init__.py
ceda_flight_pipeline/cache/id_history
ceda_flight_pipeline/cli.py
ceda_flight_pipeline/flight_client.py
ceda_flight_pipeline/logger.py
ceda_flight_pipeline/simple_client.py
ceda_flight_pipeline/tests/test_cli.py
ceda_flight_pipeline/tests/test_imports.py
ceda_flight_pipeline/updaters/moles.py
ceda_flight_pipeline/utils.py
ceda_flight_pipeline/write_flights.py
ceda_flight_pipeline-1.2.2.dist-info/LICENSE
ceda_flight_pipeline-1.2.2.dist-info/METADATA
ceda_flight_pipeline-1.2.2.dist-info/WHEEL
ceda_flight_pipeline-1.2.2.dist-info/entry_points.txt
ceda_flight_pipeline-1.2.2.dist-info/RECORD
