Metadata-Version: 2.3
Name: ceda-flight-pipeline
Version: 1.2.2
Summary: The flight-pipeline mechanism allows for uploading new flights to the STAC index using the ElasticSearch client. The flight-pipeline scripts push new records that are not currently in the index and can remove or archive pushed records on the local system. 
License: BSD 3
Author: Ioana Circu
Author-email: ioana.circu@stfc.ac.uk
Requires-Python: >=3.9,<4.0
Classifier: License :: Other/Proprietary License
Classifier: Programming Language :: Python :: 3
Classifier: Programming Language :: Python :: 3.9
Classifier: Programming Language :: Python :: 3.10
Classifier: Programming Language :: Python :: 3.11
Classifier: Programming Language :: Python :: 3.12
Classifier: Programming Language :: Python :: 3.13
Requires-Dist: certifi (>=2022.12.7,<2023.0.0)
Requires-Dist: click (>=8.1.8,<9.0.0)
Requires-Dist: elasticsearch (>=8.14.0,<9.0.0)
Requires-Dist: numpy (>=1.24.2,<2.0.0)
Requires-Dist: requests (>=2.32.4,<3.0.0)
Requires-Dist: urllib3 (>=1.26.14,<2.0.0)
